{
  "status": "scanning",
  "total_trades": 1,
  "wins": 1,
  "losses": 0,
  "total_pnl": 11.97,
  "trades": [
    {
      "symbol": "SPY",
      "direction": "CALL",
      "entry": 668.57,
      "exit": 669.77,
      "pnl": 11.97,
      "time": "15:00",
      "exitReason": "TAKE_PROFIT",
      "strike": 0,
      "expiration": "",
      "contracts": 1
    }
  ],
  "current_position": null,
  "metrics": {
    "spy_price": 662.29,
    "rsi": 100.0,
    "atr": 0.0,
    "ema9": 662.29,
    "ema21": 662.42,
    "signal": "PUT SETUP",
    "option_type": null,
    "strike": null,
    "expiration": null
  },
  "strategy": {
    "name": "RSI Mean Reversion Options Scalper",
    "description": "Trades CALLs on oversold bounces, PUTs on overbought drops",
    "call_entry": {
      "condition": "RSI < 30 (oversold) + price crosses above EMA9",
      "option": "ATM or slightly OTM CALL",
      "target": "2.0x ATR move up",
      "stop": "1.0x ATR move down"
    },
    "put_entry": {
      "condition": "RSI > 70 (overbought) + price crosses below EMA9",
      "option": "ATM or slightly OTM PUT",
      "target": "2.0x ATR move down",
      "stop": "1.0x ATR move up"
    },
    "position_size": "$500 per trade (1-2 contracts)",
    "max_hold_time": "30 minutes"
  },
  "price_history": [
    {
      "time": "2026-03-16T17:12:04.768548",
      "price": 668.0,
      "ema9": 668.0,
      "ema21": 668.0
    },
    {
      "time": "2026-03-16T17:12:34.815039",
      "price": 668.0,
      "ema9": 668.0,
      "ema21": 668.0
    },
    {
      "time": "2026-03-16T17:13:04.856094",
      "price": 668.0,
      "ema9": 668.0,
      "ema21": 668.0
    },
    {
      "time": "2026-03-16T17:13:34.927053",
      "price": 668.0,
      "ema9": 668.0,
      "ema21": 668.0
    },
    {
      "time": "2026-03-16T17:14:04.981893",
      "price": 668.0,
      "ema9": 668.0,
      "ema21": 668.0
    },
    {
      "time": "2026-03-16T17:14:16.361106",
      "price": 668.0,
      "ema9": 668.0,
      "ema21": 668.0
    },
    {
      "time": "2026-03-16T17:14:46.402337",
      "price": 668.0,
      "ema9": 668.0,
      "ema21": 668.0
    },
    {
      "time": "2026-03-16T17:15:16.455608",
      "price": 668.0,
      "ema9": 668.0,
      "ema21": 668.0
    },
    {
      "time": "2026-03-16T17:15:46.495379",
      "price": 668.0,
      "ema9": 668.0,
      "ema21": 668.0
    },
    {
      "time": "2026-03-16T17:16:16.540926",
      "price": 668.0,
      "ema9": 668.0,
      "ema21": 668.0
    },
    {
      "time": "2026-03-16T17:16:46.541990",
      "price": 662.29,
      "ema9": 666.858,
      "ema21": 667.4809090909091
    },
    {
      "time": "2026-03-16T17:17:16.542920",
      "price": 662.29,
      "ema9": 665.9444,
      "ema21": 667.0090082644629
    },
    {
      "time": "2026-03-16T17:17:46.543898",
      "price": 662.29,
      "ema9": 665.21352,
      "ema21": 666.5800075131481
    },
    {
      "time": "2026-03-16T17:18:16.544856",
      "price": 662.29,
      "ema9": 664.628816,
      "ema21": 666.1900068301346
    },
    {
      "time": "2026-03-16T17:18:46.545551",
      "price": 662.29,
      "ema9": 664.1610528,
      "ema21": 665.8354607546678
    },
    {
      "time": "2026-03-16T17:19:16.546261",
      "price": 662.29,
      "ema9": 663.7868422399999,
      "ema21": 665.5131461406071
    },
    {
      "time": "2026-03-16T17:19:46.547079",
      "price": 662.29,
      "ema9": 663.487473792,
      "ema21": 665.2201328550974
    },
    {
      "time": "2026-03-16T17:20:16.548028",
      "price": 662.29,
      "ema9": 663.2479790335999,
      "ema21": 664.9537571409976
    },
    {
      "time": "2026-03-16T17:20:46.548908",
      "price": 662.29,
      "ema9": 663.0563832268799,
      "ema21": 664.711597400907
    },
    {
      "time": "2026-03-16T17:21:16.549732",
      "price": 662.29,
      "ema9": 662.903106581504,
      "ema21": 664.4914521826427
    },
    {
      "time": "2026-03-16T17:21:46.550661",
      "price": 662.29,
      "ema9": 662.7804852652032,
      "ema21": 664.2913201660388
    },
    {
      "time": "2026-03-16T17:22:16.551981",
      "price": 662.29,
      "ema9": 662.6823882121626,
      "ema21": 664.1093819691262
    },
    {
      "time": "2026-03-16T17:22:46.552925",
      "price": 662.29,
      "ema9": 662.60391056973,
      "ema21": 663.9439836082965
    },
    {
      "time": "2026-03-16T17:23:16.553757",
      "price": 662.29,
      "ema9": 662.541128455784,
      "ema21": 663.7936214620878
    },
    {
      "time": "2026-03-16T17:23:46.554517",
      "price": 662.29,
      "ema9": 662.4909027646272,
      "ema21": 663.656928601898
    },
    {
      "time": "2026-03-16T17:24:16.555269",
      "price": 662.29,
      "ema9": 662.4507222117018,
      "ema21": 663.5326623653618
    },
    {
      "time": "2026-03-16T17:24:46.556049",
      "price": 662.29,
      "ema9": 662.4185777693614,
      "ema21": 663.4196930594198
    },
    {
      "time": "2026-03-16T17:25:16.557035",
      "price": 662.29,
      "ema9": 662.3928622154891,
      "ema21": 663.3169936903817
    },
    {
      "time": "2026-03-16T17:25:46.558084",
      "price": 662.29,
      "ema9": 662.3722897723912,
      "ema21": 663.2236306276196
    },
    {
      "time": "2026-03-16T17:26:16.559174",
      "price": 662.29,
      "ema9": 662.355831817913,
      "ema21": 663.1387551160178
    },
    {
      "time": "2026-03-16T17:26:46.559994",
      "price": 662.29,
      "ema9": 662.3426654543304,
      "ema21": 663.0615955600161
    },
    {
      "time": "2026-03-16T17:27:16.561026",
      "price": 662.29,
      "ema9": 662.3321323634643,
      "ema21": 662.9914505091056
    },
    {
      "time": "2026-03-16T17:27:46.561972",
      "price": 662.29,
      "ema9": 662.3237058907714,
      "ema21": 662.9276822810051
    },
    {
      "time": "2026-03-16T17:28:16.562826",
      "price": 662.29,
      "ema9": 662.3169647126172,
      "ema21": 662.86971116455
    },
    {
      "time": "2026-03-16T17:28:46.563619",
      "price": 662.29,
      "ema9": 662.3115717700937,
      "ema21": 662.8170101495909
    },
    {
      "time": "2026-03-16T17:29:16.564716",
      "price": 662.29,
      "ema9": 662.3072574160749,
      "ema21": 662.7691001359917
    },
    {
      "time": "2026-03-16T17:29:46.565752",
      "price": 662.29,
      "ema9": 662.3038059328599,
      "ema21": 662.7255455781743
    },
    {
      "time": "2026-03-16T17:30:16.566956",
      "price": 662.29,
      "ema9": 662.3010447462879,
      "ema21": 662.6859505256131
    },
    {
      "time": "2026-03-16T17:30:46.567963",
      "price": 662.29,
      "ema9": 662.2988357970303,
      "ema21": 662.6499550232846
    },
    {
      "time": "2026-03-16T17:31:16.568968",
      "price": 662.29,
      "ema9": 662.2970686376242,
      "ema21": 662.6172318393496
    },
    {
      "time": "2026-03-16T17:31:46.570021",
      "price": 662.29,
      "ema9": 662.2956549100993,
      "ema21": 662.5874834903178
    },
    {
      "time": "2026-03-16T17:32:16.571034",
      "price": 662.29,
      "ema9": 662.2945239280795,
      "ema21": 662.5604395366526
    },
    {
      "time": "2026-03-16T17:32:46.572067",
      "price": 662.29,
      "ema9": 662.2936191424635,
      "ema21": 662.5358541242296
    },
    {
      "time": "2026-03-16T17:33:16.573093",
      "price": 662.29,
      "ema9": 662.2928953139708,
      "ema21": 662.5135037492996
    },
    {
      "time": "2026-03-16T17:33:46.573986",
      "price": 662.29,
      "ema9": 662.2923162511767,
      "ema21": 662.493185226636
    },
    {
      "time": "2026-03-16T17:34:16.574763",
      "price": 662.29,
      "ema9": 662.2918530009413,
      "ema21": 662.4747138423963
    },
    {
      "time": "2026-03-16T17:34:46.575593",
      "price": 662.29,
      "ema9": 662.291482400753,
      "ema21": 662.4579216749057
    },
    {
      "time": "2026-03-16T17:35:16.576671",
      "price": 662.29,
      "ema9": 662.2911859206024,
      "ema21": 662.4426560680961
    },
    {
      "time": "2026-03-16T17:35:46.577788",
      "price": 662.29,
      "ema9": 662.2909487364819,
      "ema21": 662.4287782437237
    },
    {
      "time": "2026-03-16T17:36:16.578823",
      "price": 662.29,
      "ema9": 662.2907589891855,
      "ema21": 662.4161620397489
    }
  ]
}